omero_iviewer/README.rst
omero_iviewer/__init__.py
omero_iviewer/apps.py
omero_iviewer/iviewer_settings.py
omero_iviewer/urls.py
omero_iviewer/utils.py
omero_iviewer/version.py
omero_iviewer/views.py
omero_iviewer/__pycache__/__init__.cpython-39.pyc
omero_iviewer/__pycache__/utils.cpython-39.pyc
omero_iviewer/__pycache__/version.cpython-39.pyc
omero_iviewer/static/omero_iviewer/deps.js
omero_iviewer/static/omero_iviewer/main.js
omero_iviewer/static/omero_iviewer/openwith.js
omero_iviewer/static/omero_iviewer/vendors.js
omero_iviewer/static/omero_iviewer/vendors.js.LICENSE.txt
omero_iviewer/static/omero_iviewer/css/all.min.css
omero_iviewer/static/omero_iviewer/css/app.css
omero_iviewer/static/omero_iviewer/css/bootstrap.min.css
omero_iviewer/static/omero_iviewer/css/ol3-viewer.css
omero_iviewer/static/omero_iviewer/css/slider.css
omero_iviewer/static/omero_iviewer/css/spectrum.css
omero_iviewer/static/omero_iviewer/css/spinner.css
omero_iviewer/static/omero_iviewer/css/theme.css
omero_iviewer/static/omero_iviewer/css/fonts/glyphicons-halflings-regular.woff
omero_iviewer/static/omero_iviewer/css/images/arrow.png
omero_iviewer/static/omero_iviewer/css/images/arrow_arrow.png
omero_iviewer/static/omero_iviewer/css/images/arrows_dropdown.png
omero_iviewer/static/omero_iviewer/css/images/collapse-left.png
omero_iviewer/static/omero_iviewer/css/images/collapse-right.png
omero_iviewer/static/omero_iviewer/css/images/collapse.png
omero_iviewer/static/omero_iviewer/css/images/crosshair.png
omero_iviewer/static/omero_iviewer/css/images/crosshair_filled.png
omero_iviewer/static/omero_iviewer/css/images/dim_locked.png
omero_iviewer/static/omero_iviewer/css/images/dim_unlocked.png
omero_iviewer/static/omero_iviewer/css/images/drag_handle.png
omero_iviewer/static/omero_iviewer/css/images/draw_arrow.png
omero_iviewer/static/omero_iviewer/css/images/draw_ellipse.png
omero_iviewer/static/omero_iviewer/css/images/draw_label.png
omero_iviewer-0.15.0.dist-info/LICENSE
omero_iviewer-0.15.0.dist-info/METADATA
omero_iviewer-0.15.0.dist-info/WHEEL
omero_iviewer-0.15.0.dist-info/top_level.txt
omero_iviewer-0.15.0.dist-info/RECORD
