Metadata-Version: 2.1
Name: omero-iviewer
Version: 0.15.0
Summary: A Python plugin for OMERO.web
Home-page: https://github.com/ome/omero-iviewer/
Download-URL: https://github.com/ome/omero-iviewer/archive/v0.15.0.tar.gz
Author: The Open Microscopy Team
Author-email: ome-devel@lists.openmicroscopy.org.uk
License: AGPL-3.0
Keywords: OMERO.web,plugin
Classifier: Development Status :: 5 - Production/Stable
Classifier: Environment :: Web Environment
Classifier: Framework :: Django
Classifier: Intended Audience :: End Users/Desktop
Classifier: Intended Audience :: Science/Research
Classifier: Natural Language :: English
Classifier: Operating System :: OS Independent
Classifier: Programming Language :: JavaScript
Classifier: Programming Language :: Python :: 3
Classifier: Topic :: Internet :: WWW/HTTP
Classifier: Topic :: Internet :: WWW/HTTP :: Dynamic Content
Classifier: Topic :: Internet :: WWW/HTTP :: WSGI
Classifier: Topic :: Scientific/Engineering :: Visualization
Classifier: Topic :: Software Development :: Libraries :: Application Frameworks
Classifier: Topic :: Text Processing :: Markup :: HTML
Requires-Python: >=3
License-File: LICENSE
Requires-Dist: omero-web>=5.7.0
